rigid/__init__.py
python_rigid-0.1.2.dist-info/METADATA
python_rigid-0.1.2.dist-info/WHEEL
python_rigid-0.1.2.dist-info/licenses/LICENSE
python_rigid-0.1.2.dist-info/RECORD
