Metadata-Version: 2.4
Name: python-rigid
Version: 0.1.2
Summary: Universally unique lexicographically sortable identifier with cryptographical offline integrity check and meta appendix support
Project-URL: Homepage, https://github.com/bahadrix/rigid
Author: bahadrix
License-File: LICENSE
Requires-Python: >=3.11
Requires-Dist: python-ulid>=3.0.0
